HISTORY.rst
LICENSE.rst
MANIFEST.in
README.rst
setup.py
src/vdexcsv/__init__.py
src/vdexcsv/api.py
src/vdexcsv/api.rst
src/vdexcsv/script.py
src/vdexcsv/script.rst
src/vdexcsv/tests.py
src/vdexcsv.egg-info/PKG-INFO
src/vdexcsv.egg-info/SOURCES.txt
src/vdexcsv.egg-info/dependency_links.txt
src/vdexcsv.egg-info/entry_points.txt
src/vdexcsv.egg-info/requires.txt
src/vdexcsv.egg-info/top_level.txt
src/vdexcsv.egg-info/zip-safe
src/vdexcsv/testdata/test1.csv
src/vdexcsv/testdata/test2.csv
src/vdexcsv/testdata/test3.csv