Metadata-Version: 1.1
Name: vdexcsv
Version: 1.4
Summary: Converts CSV files to IMS VDEX XML (Vocabulary Definition Exchange Format)
Home-page: http://github.com/bluedynamics/vdexcsv
Author: BlueDynamics Alliance
Author-email: dev@bluedynamics.com
License: Simplified BSD
Keywords: vdex csv converter xml ims vocabulary
Platform: UNKNOWN
Classifier: Operating System :: OS Independent
Classifier: Programming Language :: Python
Classifier: Topic :: Software Development
Classifier: License :: OSI Approved :: BSD License
